README.md
setup.cfg
setup.py
fbs_tutorial_shim_mac/__init__.py
fbs_tutorial_shim_mac.egg-info/PKG-INFO
fbs_tutorial_shim_mac.egg-info/SOURCES.txt
fbs_tutorial_shim_mac.egg-info/dependency_links.txt
fbs_tutorial_shim_mac.egg-info/top_level.txt
fbs_tutorial_shim_mac/data/base
fbs_tutorial_shim_mac/data/36a0dd1cdbe0e7c4a42652ae63df0835a7bf888d/Contents/Info.plist
fbs_tutorial_shim_mac/data/36a0dd1cdbe0e7c4a42652ae63df0835a7bf888d/Contents/MacOS/MyFbsApp
fbs_tutorial_shim_mac/data/36a0dd1cdbe0e7c4a42652ae63df0835a7bf888d/Contents/MacOS/Python
fbs_tutorial_shim_mac/data/36a0dd1cdbe0e7c4a42652ae63df0835a7bf888d/Contents/MacOS/QtCore
fbs_tutorial_shim_mac/data/36a0dd1cdbe0e7c4a42652ae63df0835a7bf888d/Contents/MacOS/QtDBus
fbs_tutorial_shim_mac/data/36a0dd1cdbe0e7c4a42652ae63df0835a7bf888d/Contents/MacOS/QtGui
fbs_tutorial_shim_mac/data/36a0dd1cdbe0e7c4a42652ae63df0835a7bf888d/Contents/MacOS/QtNetwork
fbs_tutorial_shim_mac/data/36a0dd1cdbe0e7c4a42652ae63df0835a7bf888d/Contents/MacOS/QtPrintSupport
fbs_tutorial_shim_mac/data/36a0dd1cdbe0e7c4a42652ae63df0835a7bf888d/Contents/MacOS/QtQml
fbs_tutorial_shim_mac/data/36a0dd1cdbe0e7c4a42652ae63df0835a7bf888d/Contents/MacOS/QtQmlModels
fbs_tutorial_shim_mac/data/36a0dd1cdbe0e7c4a42652ae63df0835a7bf888d/Contents/MacOS/QtQuick
fbs_tutorial_shim_mac/data/36a0dd1cdbe0e7c4a42652ae63df0835a7bf888d/Contents/MacOS/QtSvg
fbs_tutorial_shim_mac/data/36a0dd1cdbe0e7c4a42652ae63df0835a7bf888d/Contents/MacOS/QtWebSockets
fbs_tutorial_shim_mac/data/36a0dd1cdbe0e7c4a42652ae63df0835a7bf888d/Contents/MacOS/QtWidgets
fbs_tutorial_shim_mac/data/36a0dd1cdbe0e7c4a42652ae63df0835a7bf888d/Contents/MacOS/base_library.zip
fbs_tutorial_shim_mac/data/36a0dd1cdbe0e7c4a42652ae63df0835a7bf888d/Contents/MacOS/libcrypto.1.1.dylib
fbs_tutorial_shim_mac/data/36a0dd1cdbe0e7c4a42652ae63df0835a7bf888d/Contents/MacOS/libncursesw.5.dylib
fbs_tutorial_shim_mac/data/36a0dd1cdbe0e7c4a42652ae63df0835a7bf888d/Contents/MacOS/libssl.1.1.dylib
fbs_tutorial_shim_mac/data/36a0dd1cdbe0e7c4a42652ae63df0835a7bf888d/Contents/MacOS/PyQt5/QtCore.abi3.so
fbs_tutorial_shim_mac/data/36a0dd1cdbe0e7c4a42652ae63df0835a7bf888d/Contents/MacOS/PyQt5/QtGui.abi3.so
